burnworks_mcp_server_fetch/__init__.py
burnworks_mcp_server_fetch/__main__.py
burnworks_mcp_server_fetch/selector_extractor.py
burnworks_mcp_server_fetch/server.py
burnworks_mcp_server_fetch/server_init.py
burnworks_mcp_server_fetch/server_patch.py
burnworks_mcp_server_fetch-0.1.0.dist-info/METADATA
burnworks_mcp_server_fetch-0.1.0.dist-info/WHEEL
burnworks_mcp_server_fetch-0.1.0.dist-info/entry_points.txt
burnworks_mcp_server_fetch-0.1.0.dist-info/licenses/LICENSE
burnworks_mcp_server_fetch-0.1.0.dist-info/RECORD
